youtube_thumbnail/__init__.py
youtube_thumbnail/__main__.py
youtube_thumbnail/cli.py
youtube_thumbnail-0.1.1.dist-info/LICENSE
youtube_thumbnail-0.1.1.dist-info/METADATA
youtube_thumbnail-0.1.1.dist-info/WHEEL
youtube_thumbnail-0.1.1.dist-info/entry_points.txt
youtube_thumbnail-0.1.1.dist-info/top_level.txt
youtube_thumbnail-0.1.1.dist-info/RECORD
